razberrylife/__init__.py
razberrylife-0.0.1.dist-info/METADATA
razberrylife-0.0.1.dist-info/WHEEL
razberrylife-0.0.1.dist-info/top_level.txt
razberrylife-0.0.1.dist-info/RECORD
