Metadata-Version: 2.1
Name: razberrylife
Version: 0.0.1
Summary: Test run
Home-page: https://github.com
Author: PkgDev
Author-email: example@example.com
License: UNKNOWN
Platform: UNKNOWN
Classifier: Programming Language :: Python :: 3
Classifier: License :: OSI Approved :: MIT License
Classifier: Operating System :: OS Independent
